airbornerf/netconfig/SchemaVersion.py
airbornerf/netconfig/__init__.py
airbornerf/netconfig/rf/AntennaPattern.py
airbornerf/netconfig/rf/Carrier.py
airbornerf/netconfig/rf/Cell.py
airbornerf/netconfig/rf/__init__.py
airbornerf/netconfig/types/UUID.py
airbornerf_netconfig-1.0.1.dist-info/METADATA
airbornerf_netconfig-1.0.1.dist-info/WHEEL
airbornerf_netconfig-1.0.1.dist-info/top_level.txt
airbornerf_netconfig-1.0.1.dist-info/RECORD
