Metadata-Version: 2.1
Name: airbornerf-netconfig
Version: 1.0.1
Summary: AirborneRF NetConfig
Home-page: https://www.airbornerf.com/
Author: Thomas Wana
Author-email: support@airbornerf.com
License: Proprietary
Platform: UNKNOWN
Requires-Dist: sqlalchemy
